LICENSE.txt
README.md
setup.cfg
setup.py
burpr/__init__.py
burpr/burpr.py
burpr3.egg-info/PKG-INFO
burpr3.egg-info/SOURCES.txt
burpr3.egg-info/dependency_links.txt
burpr3.egg-info/requires.txt
burpr3.egg-info/top_level.txt
burpr/enums/ProtocolEnum.py
burpr/enums/TransportEnum.py
burpr/enums/__init__.py
burpr/models/BurpRequest.py
burpr/models/__init__.py