Metadata-Version: 2.1
Name: burpr3
Version: 0.0.1
Summary: A Burp Suite request parser, used for aid in assessing application security functionality.
Home-page: https://github.com/krystianbajno/burpr
Author: Krystian Bajno
Author-email: krystian.bajno@gmail.com
License: MIT
Keywords: burp suite burpsuite request parser
Classifier: License :: OSI Approved :: MIT License
Classifier: Programming Language :: Python :: 3
License-File: LICENSE.txt
